{"ygPerms":{"resourceCapabilityList":[{"resourceType":"GROUP","capabilities":[{"name":"READ"},{"name":"JOIN"}]},{"resourceType":"PHOTO","capabilities":[]},{"resourceType":"FILE","capabilities":[]},{"resourceType":"MEMBER","capabilities":[]},{"resourceType":"LINK","capabilities":[]},{"resourceType":"CALENDAR","capabilities":[{"name":"READ"}]},{"resourceType":"DATABASE","capabilities":[]},{"resourceType":"POLL","capabilities":[]},{"resourceType":"MESSAGE","capabilities":[{"name":"READ"}]},{"resourceType":"PENDING_MESSAGE","capabilities":[]},{"resourceType":"ATTACHMENTS","capabilities":[{"name":"READ"}]},{"resourceType":"PHOTOMATIC_ALBUMS","capabilities":[]},{"resourceType":"MEMBERSHIP_TYPE","capabilities":[]},{"resourceType":"POST","capabilities":[{"name":"READ"}]},{"resourceType":"PIN","capabilities":[]}],"groupUrl":"ar.groups.yahoo.com","intlCode":"ar"},"comscore":"pageview_candidate","ygData":{"userId":73871954,"authorName":"Nicolás Vinacur","from":"=?iso-8859-1?Q?Nicol=E1s_Vinacur?= &lt;nvinacur@...&gt;","profile":"gring0ar","replyTo":"LIST","senderId":"pEBrO7VCLMpmiQvfD_uFyBNupTjG0PQov58zrI_lY2RwL5dHR7aAZjn4XTaoog4ABf0TdAHsvCYcrdGtSBOvfWfcpgkPhtw4cjcmuJrd7s-Z3hApVp7XdswNnOp2k7V_8PgkjA","spamInfo":{"isSpam":false,"reason":"12"},"subject":"pregunta stlosa","postDate":"1123769534","msgId":816,"canDelete":false,"contentTrasformed":false,"systemMessage":false,"headers":{"messageIdInHeader":"PDAwN2MwMWM1OWU3ZSRhY2IxODQ3MCQxNDAwYThjMEBkZWVwYmx1ZT4="},"prevInTopic":0,"nextInTopic":817,"prevInTime":815,"nextInTime":817,"topicId":816,"numMessagesInTopic":4,"msgSnippet":"Señores programadores e informaticos: Mi duda en el momento actual pasa a ser la siguiente. Supongamos que yo tengo un vector de imagenes, de tamaño n (que","rawEmail":"Return-Path: &lt;nvinacur@...&gt;\r\nX-Sender: nvinacur@...\r\nX-Apparently-To: adva@...\r\nReceived: (qmail 41252 invoked from network); 11 Aug 2005 14:12:29 -0000\r\nReceived: from unknown (66.218.66.218)\n  by m23.grp.scd.yahoo.com with QMQP; 11 Aug 2005 14:12:29 -0000\r\nReceived: from unknown (HELO avas-mr08.fibertel.com.ar) (24.232.0.221)\n  by mta3.grp.scd.yahoo.com with SMTP; 11 Aug 2005 14:12:29 -0000\r\nReceived: from OL56-122.fibertel.com.ar ([24.232.122.56]:38389 &quot;EHLO deepblue&quot;\n\tsmtp-auth: &quot;nvinacur&quot;) by avas-mr08.fibertel.com.ar with ESMTP\n\tid S229514AbVHKOMP; Thu, 11 Aug 2005 11:12:15 -0300\r\nX-Comment: RFC 2476 MSA function at avas-mr08.fibertel.com.ar logged sender identity as: nvinacur\r\nMessage-ID: &lt;007c01c59e7e$acb18470$1400a8c0@deepblue&gt;\r\nTo: &lt;adva@...&gt;\r\nDate:\tThu, 11 Aug 2005 11:12:14 -0300\r\nMIME-Version: 1.0\r\nContent-Type: multipart/alternative;\n\tboundary=&quot;----=_NextPart_000_0079_01C59E65.8736FAE0&quot;\r\nX-Priority: 3\r\nX-MSMail-Priority: Normal\r\nX-Mailer: Microsoft Outlook Express 6.00.2900.2180\r\nX-MIMEOLE: Produced By Microsoft MimeOLE V6.00.2900.2180\r\nX-Fib-Al-Info: Al\r\nX-Fib-Al-MRId: e8663f0f6d81a466ce0296610af11561\r\nX-Fib-Al-From: nvinacur@...\r\nX-eGroups-Msg-Info: 1:12:0:0\r\nFrom: =?iso-8859-1?Q?Nicol=E1s_Vinacur?= &lt;nvinacur@...&gt;\r\nSubject: pregunta stlosa\r\nX-Yahoo-Group-Post: member; u=73871954; y=Q0ZARtJKEg4jL_zLXalBzYKmjLxz8Y_kwtgRdsGtGq0vShk\r\nX-Yahoo-Profile: gring0ar\r\n\r\n\r\n------=_NextPart_000_0079_01C59E65.8736FAE0\r\nContent-Type: text/plain;\n\tcharset=&quot;iso-8859-1&quot;\r\nContent-Transfer-Encoding: quoted-printable\r\n\r\nSe=F1ores programadores e informaticos:\n\n                        Mi duda en=\r\n el momento actual pasa a ser la siguiente. Supongamos que yo tengo un vect=\r\nor de imagenes, de tama=F1o n (que sale de algun lugar del programa), que s=\r\ne llama CBlitbuf (las imagenes, y el vector se llama v):\n\nEntonces lo decla=\r\nro de alguna de las dos maneras:\n\nCBlitbuf v[MAX]; &lt;--- sobredimensiono el =\r\narreglo\nvector&lt;CBlitbuf&gt; v;  , y mas adelanto le mandaremos v.reserve(n);\n\n=\r\n\nAhora, la segunda implementacion, como supongo pensara la mayoria, es much=\r\no mas concheta y moderna. El problema es que al hacer el reserve, no esta l=\r\nlamando a los constructores de CBlitbuf, por lo tanto cuando quiero hacer a=\r\nlgo (como cargar alguna imagen) en esas instancias, el puntero (miembro de =\r\nla instancia) no esta apuntando a null entonces despues hace cualquier cosa=\r\n. Ademas, si por ejemplo overlodeo el operador =3D para poder asignarlos, e=\r\nntonces tendria que programarlo suponiendo que la instancia puede no estar =\r\ninicializada, lo que no seria coherente.\n\nSin embargo, si tengo el arreglo =\r\nsobredimensionado, SI me reserva las instancias, pero ademas llama a los co=\r\nnstructores, por lo que esta inicializada.\n\nEntonces la cuestion es, o hay =\r\nalgo de STL que no entiendo (por ejemplo, algun estandar que nunca viq ue d=\r\niga que en las estructuras solo hay que guardar punteros y no el coso en si=\r\n mismo), o bien la implementacion de STL esta mal pensada, porque a mi ente=\r\nnder, la idea de vector&lt; .. &gt; es que REEMPLACE a los arrays comunes.\n\nSin m=\r\nas, los salude atte.\n                                                      =\r\n                                              Nicolas Vinacur\n             =\r\n                                                                           =\r\n             Sabarasa Co.\r\n------=_NextPart_000_0079_01C59E65.8736FAE0\r\nContent-Type: text/html;\n\tcharset=&quot;iso-8859-1&quot;\r\nContent-Transfer-Encoding: quoted-printable\r\n\r\n&lt;!DOCTYPE HTML PUBLIC &quot;-//W3C//DTD HTML 4.0 Transitional//EN&quot;&gt;\n&lt;HTML&gt;&lt;HEAD&gt;=\r\n\n&lt;META http-equiv=3DContent-Type content=3D&quot;text/html; charset=3Diso-8859-1=\r\n&quot;&gt;\n&lt;META content=3D&quot;MSHTML 6.00.2900.2722&quot; name=3DGENERATOR&gt;\n&lt;STYLE&gt;&lt;/STYLE=\r\n&gt;\n&lt;/HEAD&gt;\n&lt;BODY bgColor=3D#ffffff&gt;\n&lt;DIV&gt;&lt;FONT face=3DArial size=3D2&gt;Se=F1or=\r\nes programadores e informaticos:&lt;/FONT&gt;&lt;/DIV&gt;\n&lt;DIV&gt;&lt;FONT face=3DArial size=\r\n=3D2&gt;&lt;/FONT&gt;&nbsp;&lt;/DIV&gt;\n&lt;DIV&gt;&lt;FONT face=3DArial size=3D2&gt;&nbsp;&nbsp;&nbsp=\r\n; &nbsp;&nbsp;&nbsp; \n&nbsp;&nbsp;&nbsp; &nbsp;&nbsp;&nbsp; &nbsp;&nbsp;&nb=\r\nsp; &nbsp;&nbsp;&nbsp; Mi \nduda en el momento actual pasa a ser la siguient=\r\ne. Supongamos que yo tengo un \nvector de imagenes, de tama=F1o n (que sale =\r\nde algun lugar del programa), que se \nllama CBlitbuf (las imagenes, y el ve=\r\nctor se llama v):&lt;/FONT&gt;&lt;/DIV&gt;\n&lt;DIV&gt;&lt;FONT face=3DArial size=3D2&gt;&lt;/FONT&gt;&nbs=\r\np;&lt;/DIV&gt;\n&lt;DIV&gt;&lt;FONT face=3DArial size=3D2&gt;Entonces lo declaro de alguna de =\r\nlas dos \nmaneras:&lt;/FONT&gt;&lt;/DIV&gt;\n&lt;DIV&gt;&lt;FONT face=3DArial size=3D2&gt;&lt;/FONT&gt;&nbs=\r\np;&lt;/DIV&gt;\n&lt;DIV&gt;&lt;FONT face=3DArial size=3D2&gt;CBlitbuf v[MAX]; &lt;--- sobredim=\r\nensiono el \narreglo&lt;/FONT&gt;&lt;/DIV&gt;\n&lt;DIV&gt;&lt;FONT face=3DArial size=3D2&gt;vector&lt=\r\n;CBlitbuf&gt; v;&nbsp; , y mas adelanto le \nmandaremos v.reserve(n);&lt;/FONT&gt;=\r\n&lt;/DIV&gt;\n&lt;DIV&gt;&lt;FONT face=3DArial size=3D2&gt;&lt;/FONT&gt;&nbsp;&lt;/DIV&gt;\n&lt;DIV&gt;&lt;FONT face=\r\n=3DArial size=3D2&gt;&lt;/FONT&gt;&nbsp;&lt;/DIV&gt;\n&lt;DIV&gt;&lt;FONT face=3DArial size=3D2&gt;Ahor=\r\na, la segunda implementacion, como supongo \npensara la mayoria, es mucho ma=\r\ns concheta y moderna. El problema es que al hacer \nel reserve, no esta llam=\r\nando a los constructores de CBlitbuf, por lo tanto \ncuando quiero hacer alg=\r\no (como cargar alguna imagen) en esas instancias, el \npuntero (miembro de l=\r\na instancia) no esta apuntando a null entonces despues hace \ncualquier cosa=\r\n. Ademas, si por ejemplo overlodeo el operador =3D para poder \nasignarlos, =\r\nentonces tendria que programarlo suponiendo que la instancia puede \nno esta=\r\nr inicializada, lo que no seria coherente.&lt;/FONT&gt;&lt;/DIV&gt;\n&lt;DIV&gt;&lt;FONT face=3DA=\r\nrial size=3D2&gt;&lt;/FONT&gt;&nbsp;&lt;/DIV&gt;\n&lt;DIV&gt;&lt;FONT face=3DArial size=3D2&gt;Sin emba=\r\nrgo, si tengo el arreglo sobredimensionado, \nSI me reserva las instancias, =\r\npero ademas llama a los constructores, por lo que \nesta inicializada.&lt;/FONT=\r\n&gt;&lt;/DIV&gt;\n&lt;DIV&gt;&lt;FONT face=3DArial size=3D2&gt;&lt;/FONT&gt;&nbsp;&lt;/DIV&gt;\n&lt;DIV&gt;&lt;FONT fac=\r\ne=3DArial size=3D2&gt;Entonces la cuestion es, o hay algo de STL que no \nentie=\r\nndo (por ejemplo, algun estandar que nunca viq ue diga que en las \nestructu=\r\nras solo hay que guardar punteros y no el coso en si mismo), o bien la \nimp=\r\nlementacion de STL esta mal pensada, porque a mi entender, la idea de \nvect=\r\nor&lt; .. &gt; es que REEMPLACE a los arrays comunes.&lt;/FONT&gt;&lt;/DIV&gt;\n&lt;DIV&gt;&lt;FO=\r\nNT face=3DArial size=3D2&gt;&lt;/FONT&gt;&nbsp;&lt;/DIV&gt;\n&lt;DIV&gt;&lt;FONT face=3DArial size=\r\n=3D2&gt;Sin mas, los salude atte.&lt;/FONT&gt;&lt;/DIV&gt;\n&lt;DIV&gt;&lt;FONT face=3DArial size=3D=\r\n2&gt;&nbsp;&nbsp;&nbsp; &nbsp;&nbsp;&nbsp; \n&nbsp;&nbsp;&nbsp; &nbsp;&nbsp;&nb=\r\nsp; &nbsp;&nbsp;&nbsp; &nbsp;&nbsp;&nbsp; \n&nbsp;&nbsp;&nbsp; &nbsp;&nbsp;&=\r\nnbsp; &nbsp;&nbsp;&nbsp; &nbsp;&nbsp;&nbsp; \n&nbsp;&nbsp;&nbsp; &nbsp;&nbsp=\r\n;&nbsp; &nbsp;&nbsp;&nbsp; &nbsp;&nbsp;&nbsp; \n&nbsp;&nbsp;&nbsp; &nbsp;&nb=\r\nsp;&nbsp; &nbsp;&nbsp;&nbsp; &nbsp;&nbsp;&nbsp; \n&nbsp;&nbsp;&nbsp; &nbsp;&=\r\nnbsp;&nbsp; &nbsp;&nbsp;&nbsp; &nbsp;&nbsp;&nbsp; \n&nbsp;&nbsp;&nbsp; &nbsp=\r\n;&nbsp;&nbsp; &nbsp;&nbsp;&nbsp; Nicolas \nVinacur&lt;/FONT&gt;&lt;/DIV&gt;\n&lt;DIV&gt;&lt;FONT f=\r\nace=3DArial \nsize=3D2&gt;&nbsp;&nbsp;&nbsp;&nbsp;&nbsp;&nbsp;&nbsp;&nbsp;&nbsp=\r\n;&nbsp;&nbsp;&nbsp;&nbsp;&nbsp;&nbsp;&nbsp;&nbsp;&nbsp;&nbsp;&nbsp;&nbsp;&n=\r\nbsp;&nbsp;&nbsp;&nbsp;&nbsp;&nbsp;&nbsp;&nbsp;&nbsp;&nbsp;&nbsp;&nbsp;&nbsp=\r\n;&nbsp;&nbsp;&nbsp;&nbsp;&nbsp;&nbsp;&nbsp;&nbsp;&nbsp;&nbsp;&nbsp;&nbsp;&n=\r\nbsp;&nbsp;&nbsp;&nbsp;&nbsp;&nbsp;&nbsp;&nbsp;&nbsp;&nbsp;&nbsp;&nbsp;&nbsp=\r\n;&nbsp;&nbsp;&nbsp;&nbsp;&nbsp;&nbsp;&nbsp;&nbsp;&nbsp;&nbsp;&nbsp;&nbsp;&n=\r\nbsp;&nbsp;&nbsp;&nbsp;&nbsp;&nbsp;&nbsp;&nbsp;&nbsp;&nbsp;&nbsp;&nbsp;&nbsp=\r\n;&nbsp;&nbsp;&nbsp;&nbsp;&nbsp;&nbsp;&nbsp;&nbsp;&nbsp;&nbsp;&nbsp;&nbsp;&n=\r\nbsp;&nbsp;&nbsp;&nbsp;&nbsp;Sabarasa \nCo.&lt;/FONT&gt;&lt;/DIV&gt;&lt;/BODY&gt;&lt;/HTML&gt;\n\r\n------=_NextPart_000_0079_01C59E65.8736FAE0--\r\n\n"}}