{"ygPerms":{"resourceCapabilityList":[{"resourceType":"GROUP","capabilities":[{"name":"READ"},{"name":"WELCOME_MSG"}]},{"resourceType":"PHOTO","capabilities":[{"name":"READ"},{"name":"UPLOAD"},{"name":"UPLOADTEMP"}]},{"resourceType":"FILE","capabilities":[{"name":"READ"},{"name":"CREATE"}]},{"resourceType":"MEMBER","capabilities":[{"name":"READ"}]},{"resourceType":"LINK","capabilities":[{"name":"CREATE"},{"name":"READ"}]},{"resourceType":"CALENDAR","capabilities":[{"name":"READ"}]},{"resourceType":"DATABASE","capabilities":[{"name":"CREATE"},{"name":"READ_DATA"},{"name":"READ"}]},{"resourceType":"POLL","capabilities":[{"name":"READ"},{"name":"VOTE"},{"name":"CREATE"}]},{"resourceType":"MESSAGE","capabilities":[{"name":"CREATE"},{"name":"READ"}]},{"resourceType":"PENDING_MESSAGE","capabilities":[]},{"resourceType":"ATTACHMENTS","capabilities":[{"name":"READ"}]},{"resourceType":"PHOTOMATIC_ALBUMS","capabilities":[{"name":"READ"},{"name":"UPLOAD"}]},{"resourceType":"MEMBERSHIP_TYPE","capabilities":[{"name":"READ"}]},{"resourceType":"POST","capabilities":[{"name":"CREATE"},{"name":"READ"}]},{"resourceType":"PIN","capabilities":[{"name":"CREATE"},{"name":"UPDATE"},{"name":"READ"},{"name":"DELETE"}]}],"subStatus":"NORMAL","groupUrl":"ar.groups.yahoo.com","intlCode":"ar"},"comscore":"pageview_candidate","ygData":{"userId":175575751,"authorName":"osqar@ubbi.com","from":"&lt;osqar@...&gt;","profile":"oscarkp","replyTo":"LIST","senderId":"F2uDWaYZmtCLURQqMJT3FqcoegXMutnPcnT67_kYE0Zc9P8q_flBG9bFcaWhuzxtKFwxWzQtTg","spamInfo":{"isSpam":false,"reason":"0"},"subject":"RE: [JuegosAr] susc","postDate":"1098124827","msgId":11706,"canDelete":false,"contentTrasformed":false,"systemMessage":false,"headers":{"messageIdInHeader":"PDIwMDQxMDE4MTU0MDI3Ljk4NEZENjYxLkU3MjlCN0VBQDE3Mi4xNi4xLjY4Pg=="},"prevInTopic":0,"nextInTopic":0,"prevInTime":11705,"nextInTime":11707,"topicId":11706,"numMessagesInTopic":1,"msgSnippet":"... Nadie hablo de mentir, la verdad es que yo no estuve cuando Moreno se murio asi que no te podria decir si eso es cierto o no. Si segun la histioria dicen","rawEmail":"Return-Path: &lt;osqar@...&gt;\r\nX-Sender: osqar@...\r\nX-Apparently-To: JuegosAR@...\r\nReceived: (qmail 77130 invoked from network); 18 Oct 2004 18:43:53 -0000\r\nReceived: from unknown (66.218.66.218)\n  by m10.grp.scd.yahoo.com with QMQP; 18 Oct 2004 18:43:53 -0000\r\nReceived: from unknown (HELO cumeils.prima.com.ar) (200.42.0.157)\n  by mta3.grp.scd.yahoo.com with SMTP; 18 Oct 2004 18:43:52 -0000\r\nReceived: (qmail 52622 invoked from network); 18 Oct 2004 18:40:27 -0000\r\nReceived: from unknown (172.16.1.68)\n  by cumeil2.int.prima.com.ar with SMTP; 18 Oct 2004 18:40:27 -0000\r\nMessage-ID: &lt;20041018154027.984FD661.E729B7EA@172.16.1.68&gt;\r\nTo: &lt;JuegosAR@...&gt;\r\nDate: Mon, 18 Oct 2004 15:40:27 -0300\r\nX-Priority: 3\r\nContent-Transfer-Encoding: quoted-printable\r\nContent-Type: text/plain; charset=&quot;iso-8859-1&quot;\r\nContent-Disposition: inline\r\nContent-Length: 3567\r\nX-SenderIP: 200.3.94.200\r\nX-eGroups-Remote-IP: 200.42.0.157\r\nFrom: &lt;osqar@...&gt;\r\nReply-To: &lt;osqar@...&gt;\r\nSubject: =?iso-8859-1?Q?RE:=20[JuegosAr]=20susc?=\r\nX-Yahoo-Group-Post: member; u=175575751\r\nX-Yahoo-Profile: oscarkp\r\n\r\n\n&gt; La pregunta es si se justifica mentir, (porque no decir la verdad es  \n&gt;=\r\n mentir, =BFno?) en nombre de un romanticismo que no es innato, sino  \n&gt; &quot;e=\r\nmbutido&quot; a la fuerza en los ni=F1os. Los nenes no nacen con la necesidad  \n=\r\n&gt; de creer en Pap=E1 Noel, nosotros se la inculcamos a un grado tal que se =\r\nles  \n&gt; vuelve necesaria. Tampoco nacen con la necesidad de creer que Moren=\r\no muri=F3  \n&gt; espontaneamente, y sin embargo se empe=F1an en hacerles creer=\r\n eso, porque de  \n&gt; lo contrario implicaria que los pol=EDticos de la =E9po=\r\nca se peleaban entre  \n&gt; ellos y eran capaces de matar por poder...=A1que n=\r\novedad!\n\n Nadie hablo de mentir, la verdad es que yo no estuve cuando Moren=\r\no se murio asi que no te podria decir si eso es cierto o no. Si segun la hi=\r\nstioria dicen que  Moreno murio &quot;espontaneamente&quot; y despues por que se busc=\r\na hacer una lectura de la historia distinta para apoyar determinada postura=\r\n politica vos vas a llamar mentiroso al que te ense=F1o la primera version =\r\nde la muerte de Moreno?.\n\n&gt; De la misma manera que decir solamente que dura=\r\nnte la =E9poca de los Nazis  \n&gt; en Alemania se construyeron mas escuelas qu=\r\ne en todo el resto de su  \n&gt; historia es mentir por no decir toda la verdad=\r\n, tambien es mentir si uno  \n&gt; pretende ocultar las miserias y mezquindades=\r\n (que junto con sus ideales  \n&gt; terminan conformando lo que los impuls=F3 a=\r\n ser lo que fueron) de las  \n&gt; personas (eran eso en definitiva, no naciero=\r\nn de bronce) que forjaron este  \n&gt; pais.\n\n Eso es ser tendensioso, vos no p=\r\nodes fabricar una verdad de acuerdo a si la cantidad de muertos o si los mu=\r\nertos son mas validos que otros o no. La verdad es que el regimen nazi lleg=\r\no a donde llego porque los apoyo el pueblo aleman y no se puede decir que t=\r\nodo el pueblo aleman fueron una manga de asesinos.\n El pais no se forjo en =\r\nbase a mezquindades y miserias sino justamente combatiento a estas. Ejemplo=\r\ns de mezquindades y miserias sobran pero lo que hay que resaltar es como se=\r\n combatio a las mismas para formar un pais soberano. \n\n&gt; Ahora, si no podem=\r\nos ponernos de acuerdo en eso, cambiemosle por lo menos  \n&gt; el nombre a lo =\r\nque se ense=F1a en la escuela...saquemos la palabra historia  \n&gt; y pongamos=\r\nl=E9 &quot;Leyendas aleccionadoras, no faltas de moraleja, basadas en  \n&gt; hechos=\r\n y personajes reales&quot;.\n\nA lo que no hay que llamar historia es a lo que se =\r\npretende hacer con revisar la historia porque se agregan muchas pasiones ac=\r\ntuales a echos que pasaron hace mucho tiempo, a mas de un militante de la c=\r\nomunidad gay por ejemplo le gustaria que se comprobase que Belgrano era gay=\r\n para refregarselo en la cara a la derecha antigay y como ese hay muchos ma=\r\ns casos... ese tipo de cuestiones nada tiene que ver con historia y a nadie=\r\n le interesa saber lo que hacia belgrano con su culo pero si lo mucho que c=\r\nontribuyo para la formacion de este pais.\n\n&gt; Las personas tienen defectos. =\r\nLos ideales van mas alla de los defectos de  \n&gt; cada persona. Eso es lo que=\r\n hay que ense=F1arles a los chicos.\n\n Los chicos ya saben que las personas =\r\ntienen defectos, lo que no saben es como defender los ideales porque cada v=\r\nez mas se ponen en duda sin ningun objetivo claro a modelos de estos ideale=\r\ns.\n__________________________________________________\n\nTodav=EDa no ten=E9s=\r\n tu Ubbi Mail? Obtenelo ahora! - http://mail.ubbi.com\n\nDescarg=E1 Gratis el=\r\n nuevo Internet Explorer 6.0, el mejor software para actualizar tu PC.\nhttp=\r\n://www.ciudad.com.ar/ar/servicios/ie/\n\n\n"}}