{"ygPerms":{"resourceCapabilityList":[{"resourceType":"GROUP","capabilities":[{"name":"READ"},{"name":"WELCOME_MSG"}]},{"resourceType":"PHOTO","capabilities":[{"name":"READ"},{"name":"UPLOAD"},{"name":"UPLOADTEMP"}]},{"resourceType":"FILE","capabilities":[{"name":"READ"},{"name":"CREATE"}]},{"resourceType":"MEMBER","capabilities":[{"name":"READ"}]},{"resourceType":"LINK","capabilities":[{"name":"CREATE"},{"name":"READ"}]},{"resourceType":"CALENDAR","capabilities":[{"name":"READ"}]},{"resourceType":"DATABASE","capabilities":[{"name":"READ_DATA"},{"name":"READ"},{"name":"CREATE"}]},{"resourceType":"POLL","capabilities":[{"name":"READ"},{"name":"VOTE"},{"name":"CREATE"}]},{"resourceType":"MESSAGE","capabilities":[{"name":"CREATE"},{"name":"READ"}]},{"resourceType":"PENDING_MESSAGE","capabilities":[]},{"resourceType":"ATTACHMENTS","capabilities":[{"name":"READ"}]},{"resourceType":"PHOTOMATIC_ALBUMS","capabilities":[{"name":"READ"},{"name":"UPLOAD"}]},{"resourceType":"MEMBERSHIP_TYPE","capabilities":[{"name":"READ"}]},{"resourceType":"POST","capabilities":[{"name":"READ"},{"name":"CREATE"}]},{"resourceType":"PIN","capabilities":[{"name":"DELETE"},{"name":"READ"},{"name":"UPDATE"},{"name":"CREATE"}]}],"subStatus":"NORMAL","groupUrl":"ar.groups.yahoo.com","intlCode":"ar"},"comscore":"pageview_candidate","ygData":{"userId":235427263,"authorName":"Andres Martinez Quijano","from":"&quot;Andres Martinez Quijano&quot; &lt;tulsidas@...&gt;","profile":"quixote_arg","replyTo":"LIST","senderId":"ta_ZLZHAIaDkvLMSeWEu9lGq5EnUITo2dUpLGAxHkLljCoDPvArajeP2B6cC15q2IddA1-Jp-CEqRNnjzxZ_xSUkL-KhySqWvNM_9JkCqFIk9y1BiQ","spamInfo":{"isSpam":false,"reason":"0"},"subject":"Re: [JuegosAr] Java para NDS","postDate":"1188170605","msgId":17101,"canDelete":false,"contentTrasformed":false,"systemMessage":false,"headers":{"messageIdInHeader":"PGNjNDAyMjA2MDcwODI2MTYyM2s2MGQyM2U5NXAxZTQ3NTMxNWI0NmQyODEzQG1haWwuZ21haWwuY29tPg==","inReplyToHeader":"PGIwODM0OWVlMDcwODI2MTQyOXQxN2NlZmE0czMxMDQyODllZTJlYTA0YTNAbWFpbC5nbWFpbC5jb20+","referencesHeader":"PGIwODM0OWVlMDcwODI2MTQyOXQxN2NlZmE0czMxMDQyODllZTJlYTA0YTNAbWFpbC5nbWFpbC5jb20+"},"prevInTopic":17100,"nextInTopic":0,"prevInTime":17100,"nextInTime":17102,"topicId":17100,"numMessagesInTopic":2,"msgSnippet":"muy bueno para portar fácilmente juegos hechos para celular a la DS ... muy bueno para portar fácilmente juegos hechos para celular a la DS On 8/26/07, Eka","rawEmail":"Return-Path: &lt;tulsidas@...&gt;\r\nX-Sender: tulsidas@...\r\nX-Apparently-To: JuegosAR@...\r\nReceived: (qmail 28894 invoked from network); 26 Aug 2007 23:23:27 -0000\r\nReceived: from unknown (66.218.66.70)\n  by m37.grp.scd.yahoo.com with QMQP; 26 Aug 2007 23:23:27 -0000\r\nReceived: from unknown (HELO nz-out-0506.google.com) (64.233.162.232)\n  by mta12.grp.scd.yahoo.com with SMTP; 26 Aug 2007 23:23:27 -0000\r\nReceived: by nz-out-0506.google.com with SMTP id x7so858204nzc\n        for &lt;JuegosAR@...&gt;; Sun, 26 Aug 2007 16:23:26 -0700 (PDT)\r\nReceived: by 10.142.156.2 with SMTP id d2mr311561wfe.1188170605675;\n        Sun, 26 Aug 2007 16:23:25 -0700 (PDT)\r\nReceived: by 10.143.41.3 with HTTP; Sun, 26 Aug 2007 16:23:25 -0700 (PDT)\r\nMessage-ID: &lt;cc4022060708261623k60d23e95p1e475315b46d2813@...&gt;\r\nDate: Sun, 26 Aug 2007 20:23:25 -0300\r\nTo: JuegosAR@...\r\nIn-Reply-To: &lt;b08349ee0708261429t17cefa4s3104289ee2ea04a3@...&gt;\r\nMIME-Version: 1.0\r\nContent-Type: multipart/alternative; \n\tboundary=&quot;----=_Part_104494_32732281.1188170605637&quot;\r\nReferences: &lt;b08349ee0708261429t17cefa4s3104289ee2ea04a3@...&gt;\r\nX-eGroups-Msg-Info: 1:0:0:0:0\r\nFrom: &quot;Andres Martinez Quijano&quot; &lt;tulsidas@...&gt;\r\nSubject: Re: [JuegosAr] Java para NDS\r\nX-Yahoo-Group-Post: member; u=235427263; y=qhPTIVRAaQ3g9PiQIfAzCsDHYG1utGTFRXAEhxRiILNemihoTkk\r\nX-Yahoo-Profile: quixote_arg\r\n\r\n\r\n------=_Part_104494_32732281.1188170605637\r\nContent-Type: text/plain; charset=ISO-8859-1\r\nContent-Disposition: inline\r\n\r\n[ Attachment content not displayed ]\r\n------=_Part_104494_32732281.1188170605637\r\nContent-Type: text/html; charset=ISO-8859-1\r\nContent-Disposition: inline\r\n\r\n[ Attachment content not displayed ]\r\n------=_Part_104494_32732281.1188170605637--\r\n\n"}}